cli/__init__.py
cli/initializer.py
cli/spsm.py
cli/data/spsm.toml
jmanager/__init__.py
jmanager/jar_manager.py
jmanager/handlers/__init__.py
jmanager/handlers/download_handler.py
jmanager/handlers/jar_data_handler.py
server/__init__.py
server/server_commander.py
server/server_wrapper.py
server/commands/__init__.py
server/commands/deactivate.py
server/commands/exit.py
server/commands/help.py
server/commands/prepare_for_attach.py
server/commands/refresh.py
server/commands/reload.py
server/commands/restart.py
server/commands/say.py
server/commands/start.py
server/commands/stop.py
server/enums/__init__.py
server/enums/log_levels.py
server/handlers/__init__.py
server/handlers/backup_handler.py
server/handlers/error_handler.py
server/handlers/input_handler.py
server/handlers/log_handler.py
server/handlers/output_handler.py
server/handlers/screen_handler.py
utils/__init__.py
utils/config.py
utils/io.py
utils/constants/__init__.py
utils/constants/defaults.py
spsm-0.1.2.dist-info/LICENSE.md
spsm-0.1.2.dist-info/METADATA
spsm-0.1.2.dist-info/WHEEL
spsm-0.1.2.dist-info/entry_points.txt
spsm-0.1.2.dist-info/top_level.txt
spsm-0.1.2.dist-info/RECORD
