Metadata-Version: 2.1
Name: spsm
Version: 0.1.2
Summary: A simple minecraft server manager
Author-email: Chris Morgan <cnmorgan@gmail.com>
Maintainer-email: Chris Morgan <cnmorgan@gmail.com>
License: GNU GENERAL PUBLIC LICENSE
Project-URL: Homepage, https://github.com/cnmorgan/spsm
Project-URL: Source, https://github.com/cnmorgan/spsm
Keywords: minecraft,cli,server
Classifier: Development Status :: 3 - Alpha
Classifier: Intended Audience :: Developers
Classifier: Topic :: Games/Entertainment
Classifier: License :: OSI Approved :: MIT License
Classifier: Programming Language :: Python :: 3
Classifier: Programming Language :: Python :: 3.7
Classifier: Programming Language :: Python :: 3.8
Classifier: Programming Language :: Python :: 3.9
Classifier: Programming Language :: Python :: 3.10
Classifier: Programming Language :: Python :: 3.11
Classifier: Programming Language :: Python :: 3 :: Only
Requires-Python: >=3.8
License-File: LICENSE.md
Requires-Dist: click (>=8.1)
Requires-Dist: requests (>=2.28)
Requires-Dist: tomli (>=2.0)
Provides-Extra: dev
Requires-Dist: bump2version ; extra == 'dev'
